alcove/__init__.py
alcove/core.py
alcove/exceptions.py
alcove/paths.py
alcove/schemas.py
alcove/snapshots.py
alcove/steps.py
alcove/table_metadata.py
alcove/tables.py
alcove/types.py
alcove/utils.py
alcove/schemas/alcove-v1.schema.json
alcove/schemas/snapshot-v1.schema.json
alcove/schemas/table-config-v1.schema.json
alcove/schemas/table-v1.schema.json
alcove-0.2.1.dist-info/METADATA
alcove-0.2.1.dist-info/WHEEL
alcove-0.2.1.dist-info/entry_points.txt
alcove-0.2.1.dist-info/licenses/LICENSE
alcove-0.2.1.dist-info/RECORD
