Metadata-Version: 2.4
Name: alcove
Version: 0.2.1
Summary: An opinionated small-scale ETL framework for managing data files and directories in a content-addressable way.
Project-URL: Homepage, https://github.com/larsyencken/alcove
Project-URL: Repository, https://github.com/larsyencken/alcove
Project-URL: Bug Tracker, https://github.com/larsyencken/alcove/issues
Author-email: Lars Yencken <lars@yencken.org>
License-Expression: MIT
License-File: LICENSE
Keywords: content-addressable,data-engineering,data-lake,etl
Classifier: Development Status :: 3 - Alpha
Classifier: Intended Audience :: Developers
Classifier: Programming Language :: Python :: 3
Classifier: Programming Language :: Python :: 3.12
Classifier: Topic :: Software Development :: Libraries :: Python Modules
Requires-Python: >=3.12
Requires-Dist: boto3>=1.34.145
Requires-Dist: duckdb>=1.0.0
Requires-Dist: jsonschema>=4.23.0
Requires-Dist: polars>=1.4.0
Requires-Dist: python-dotenv>=1.0.1
Requires-Dist: pyyaml>=6.0.1
Requires-Dist: rich>=13.7.1
Requires-Dist: ruff>=0.5.5
